keybaseapi/__init__.py
keybaseapi/api.py
keybaseapi/exc.py
keybaseio_api-1.0.3.post1.dist-info/RECORD
keybaseio_api-1.0.3.post1.dist-info/top_level.txt
keybaseio_api-1.0.3.post1.dist-info/METADATA
keybaseio_api-1.0.3.post1.dist-info/WHEEL
keybaseio_api-1.0.3.post1.dist-info/DESCRIPTION.rst
keybaseio_api-1.0.3.post1.dist-info/metadata.json
