Metadata-Version: 2.0
Name: keybaseio-api
Version: 1.0.3.post1
Summary: A keybase.io API for Python 3
Home-page: https://github.com/SkierPGP/keybase-python3
Author: Isaac Dickinson
Author-email: eyesismine@gmail.com
License: GPLv3
Platform: UNKNOWN
Classifier: Development Status :: 4 - Beta
Classifier: Intended Audience :: Developers
Classifier: License :: OSI Approved :: GNU General Public License v3 (GPLv3)
Classifier: Programming Language :: Python :: 3 :: Only
Classifier: Topic :: Security
Classifier: Topic :: Security :: Cryptography
Requires-Dist: requests
Requires-Dist: ConfigMaster (>=2.3.5)
Requires-Dist: py-pgp (>=0.0.1)
